mdtcollections
tests
